[{"_id":"STEAM_0:0:53676237","name":"Gizmo","steamID":"STEAM_0:0:53676237","team":"Bravona","matches":2,"wins":1,"losses":1,"draws":0,"goals":0,"assists":0,"shots":0,"shotsontarget":0,"passes":15,"passescompleted":5,"interceptions":7,"saves":0,"fouls":0,"yellowcards":0,"redcards":0,"owngoals":0,"offsides":0,"distancecovered":1928,"possession":1.5,"corners":0,"throwins":3,"penalties":0,"freekicks":0,"tackles":5,"tacklescompleted":1,"foulssuffered":0,"savescaught":0,"goalkicks":0,"goalsconceded":0,"secondsplayed":3266,"keypasses":0,"chancescreated":0,"secondassists":0},{"_id":"STEAM_0:0:79007256","name":"IvNN","steamID":"STEAM_0:0:79007256","team":"Bravona","matches":3,"wins":2,"losses":1,"draws":0,"goals":2,"assists":1,"shots":7,"shotsontarget":7,"passes":74,"passescompleted":48,"interceptions":22,"saves":0,"fouls":0,"yellowcards":0,"redcards":0,"owngoals":0,"offsides":1,"distancecovered":5523.333333333333,"possession":7.333333333333333,"corners":0,"throwins":10,"penalties":0,"freekicks":3,"tackles":1,"tacklescompleted":0,"foulssuffered":0,"savescaught":0,"goalkicks":0,"goalsconceded":0,"secondsplayed":13078,"keypasses":0,"chancescreated":0,"secondassists":0},{"_id":"STEAM_0:1:180525897","name":"LisandroMagallan","steamID":"STEAM_0:1:180525897","team":"Bravona","matches":2,"wins":0,"losses":1,"draws":1,"goals":1,"assists":0,"shots":3,"shotsontarget":3,"passes":23,"passescompleted":11,"interceptions":10,"saves":1,"fouls":0,"yellowcards":0,"redcards":0,"owngoals":0,"offsides":0,"distancecovered":3728.5,"possession":3,"corners":3,"throwins":2,"penalties":0,"freekicks":0,"tackles":9,"tacklescompleted":3,"foulssuffered":0,"savescaught":0,"goalkicks":4,"goalsconceded":4,"secondsplayed":6326,"keypasses":0,"chancescreated":0,"secondassists":0},{"_id":"STEAM_0:1:54634906","name":"Lu13144","steamID":"STEAM_0:1:54634906","team":"Bravona","matches":14,"wins":5,"losses":7,"draws":2,"goals":19,"assists":6,"shots":78,"shotsontarget":58,"passes":383,"passescompleted":189,"interceptions":116,"saves":0,"fouls":1,"yellowcards":1,"redcards":0,"owngoals":0,"offsides":2,"distancecovered":6242.285714285715,"possession":11.5,"corners":7,"throwins":27,"penalties":0,"freekicks":7,"tackles":7,"tacklescompleted":0,"foulssuffered":4,"savescaught":0,"goalkicks":0,"goalsconceded":0,"secondsplayed":77533,"keypasses":0,"chancescreated":0,"secondassists":0},{"_id":"STEAM_0:1:164981041","name":"MRC_","steamID":"STEAM_0:1:164981041","team":"Bravona","matches":5,"wins":1,"losses":2,"draws":2,"goals":0,"assists":0,"shots":3,"shotsontarget":1,"passes":121,"passescompleted":58,"interceptions":56,"saves":4,"fouls":1,"yellowcards":1,"redcards":0,"owngoals":0,"offsides":0,"distancecovered":6543.2,"possession":6.6,"corners":0,"throwins":26,"penalties":0,"freekicks":3,"tackles":5,"tacklescompleted":1,"foulssuffered":0,"savescaught":4,"goalkicks":4,"goalsconceded":4,"secondsplayed":27053,"keypasses":0,"chancescreated":0,"secondassists":0},{"_id":"STEAM_0:0:160196285","name":"MartinCho","steamID":"STEAM_0:0:160196285","team":"Bravona","matches":8,"wins":1,"losses":5,"draws":2,"goals":0,"assists":4,"shots":1,"shotsontarget":1,"passes":214,"passescompleted":149,"interceptions":61,"saves":113,"fouls":0,"yellowcards":0,"redcards":0,"owngoals":0,"offsides":0,"distancecovered":2194.25,"possession":5.125,"corners":0,"throwins":0,"penalties":0,"freekicks":0,"tackles":1,"tacklescompleted":0,"foulssuffered":0,"savescaught":88,"goalkicks":53,"goalsconceded":49,"secondsplayed":45990,"keypasses":0,"chancescreated":0,"secondassists":0},{"_id":"STEAM_0:1:444044659","name":"Meza","steamID":"STEAM_0:1:444044659","team":"Bravona","matches":14,"wins":5,"losses":7,"draws":2,"goals":11,"assists":4,"shots":41,"shotsontarget":29,"passes":308,"passescompleted":158,"interceptions":78,"saves":70,"fouls":2,"yellowcards":1,"redcards":1,"owngoals":0,"offsides":3,"distancecovered":4452.785714285715,"possession":9.142857142857142,"corners":2,"throwins":16,"penalties":1,"freekicks":5,"tackles":57,"tacklescompleted":7,"foulssuffered":3,"savescaught":44,"goalkicks":74,"goalsconceded":50,"secondsplayed":165760,"keypasses":0,"chancescreated":0,"secondassists":0},{"_id":"STEAM_0:1:68456910","name":"Palermito","steamID":"STEAM_0:1:68456910","team":"Bravona","matches":1,"wins":0,"losses":1,"draws":0,"goals":0,"assists":0,"shots":1,"shotsontarget":0,"passes":17,"passescompleted":8,"interceptions":1,"saves":0,"fouls":0,"yellowcards":0,"redcards":0,"owngoals":0,"offsides":0,"distancecovered":5830,"possession":7,"corners":0,"throwins":1,"penalties":0,"freekicks":0,"tackles":0,"tacklescompleted":0,"foulssuffered":0,"savescaught":0,"goalkicks":0,"goalsconceded":0,"secondsplayed":4426,"keypasses":0,"chancescreated":0,"secondassists":0},{"_id":"STEAM_0:0:104570690","name":"WINDzOR","steamID":"STEAM_0:0:104570690","team":"Bravona","matches":11,"wins":4,"losses":5,"draws":2,"goals":10,"assists":3,"shots":33,"shotsontarget":24,"passes":226,"passescompleted":90,"interceptions":75,"saves":0,"fouls":1,"yellowcards":1,"redcards":0,"owngoals":0,"offsides":8,"distancecovered":6522.636363636364,"possession":11.545454545454545,"corners":6,"throwins":33,"penalties":0,"freekicks":3,"tackles":33,"tacklescompleted":0,"foulssuffered":3,"savescaught":0,"goalkicks":0,"goalsconceded":0,"secondsplayed":83788,"keypasses":0,"chancescreated":0,"secondassists":0},{"_id":"STEAM_0:0:104244544","name":"ELDROGA#Moshi","steamID":"STEAM_0:0:104244544","team":"Caballeros de la Birra","matches":14,"wins":6,"losses":7,"draws":1,"goals":1,"assists":2,"shots":4,"shotsontarget":1,"passes":411,"passescompleted":217,"interceptions":116,"saves":157,"fouls":0,"yellowcards":0,"redcards":0,"owngoals":0,"offsides":0,"distancecovered":1650.4285714285713,"possession":6.571428571428571,"corners":0,"throwins":0,"penalties":0,"freekicks":1,"tackles":0,"tacklescompleted":0,"foulssuffered":0,"savescaught":115,"goalkicks":119,"goalsconceded":39,"secondsplayed":77232,"keypasses":0,"chancescreated":0,"secondassists":0},{"_id":"STEAM_0:1:94952569","name":"II SeBek","steamID":"STEAM_0:1:94952569","team":"Caballeros de la Birra","matches":1,"wins":0,"losses":1,"draws":0,"goals":0,"assists":0,"shots":2,"shotsontarget":1,"passes":36,"passescompleted":28,"interceptions":9,"saves":0,"fouls":0,"yellowcards":0,"redcards":0,"owngoals":0,"offsides":0,"distancecovered":6033,"possession":9,"corners":0,"throwins":2,"penalties":0,"freekicks":0,"tackles":0,"tacklescompleted":0,"foulssuffered":1,"savescaught":0,"goalkicks":0,"goalsconceded":0,"secondsplayed":5645,"keypasses":0,"chancescreated":0,"secondassists":0},{"_id":"STEAM_0:1:104176669","name":"Javier Pastore #m.","steamID":"STEAM_0:1:104176669","team":"Caballeros de la Birra","matches":14,"wins":6,"losses":7,"draws":1,"goals":8,"assists":12,"shots":42,"shotsontarget":32,"passes":244,"passescompleted":129,"interceptions":75,"saves":0,"fouls":2,"yellowcards":1,"redcards":0,"owngoals":0,"offsides":6,"distancecovered":5140.928571428572,"possession":7.071428571428571,"corners":18,"throwins":31,"penalties":0,"freekicks":4,"tackles":113,"tacklescompleted":25,"foulssuffered":3,"savescaught":0,"goalkicks":0,"goalsconceded":0,"secondsplayed":60307,"keypasses":0,"chancescreated":0,"secondassists":0},{"_id":"STEAM_0:0:151744899","name":"SeBek #m.","steamID":"STEAM_0:0:151744899","team":"Caballeros de la Birra","matches":12,"wins":3,"losses":8,"draws":1,"goals":1,"assists":2,"shots":13,"shotsontarget":4,"passes":295,"passescompleted":131,"interceptions":130,"saves":0,"fouls":1,"yellowcards":0,"redcards":0,"owngoals":0,"offsides":0,"distancecovered":5246.666666666667,"possession":5.916666666666667,"corners":1,"throwins":46,"penalties":0,"freekicks":3,"tackles":21,"tacklescompleted":5,"foulssuffered":1,"savescaught":0,"goalkicks":0,"goalsconceded":0,"secondsplayed":58583,"keypasses":0,"chancescreated":0,"secondassists":0},{"_id":"STEAM_0:0:452411951","name":"baphomet #AraSanJuan","steamID":"STEAM_0:0:452411951","team":"Caballeros de la Birra","matches":6,"wins":1,"losses":4,"draws":1,"goals":3,"assists":3,"shots":14,"shotsontarget":10,"passes":45,"passescompleted":23,"interceptions":18,"saves":0,"fouls":2,"yellowcards":2,"redcards":0,"owngoals":0,"offsides":3,"distancecovered":2278,"possession":4.333333333333333,"corners":1,"throwins":8,"penalties":0,"freekicks":4,"tackles":11,"tacklescompleted":3,"foulssuffered":2,"savescaught":0,"goalkicks":0,"goalsconceded":0,"secondsplayed":15397,"keypasses":0,"chancescreated":0,"secondassists":0},{"_id":"STEAM_0:1:97787686","name":"xPecMenn#m","steamID":"STEAM_0:1:97787686","team":"Caballeros de la Birra","matches":14,"wins":6,"losses":7,"draws":1,"goals":4,"assists":3,"shots":39,"shotsontarget":27,"passes":427,"passescompleted":175,"interceptions":171,"saves":0,"fouls":2,"yellowcards":1,"redcards":0,"owngoals":0,"offsides":0,"distancecovered":6993.571428571428,"possession":8.428571428571429,"corners":0,"throwins":71,"penalties":0,"freekicks":5,"tackles":36,"tacklescompleted":12,"foulssuffered":1,"savescaught":0,"goalkicks":1,"goalsconceded":0,"secondsplayed":73398,"keypasses":0,"chancescreated":0,"secondassists":0},{"_id":"STEAM_0:0:427374257","name":"Armani","steamID":"STEAM_0:0:427374257","team":"Colchester United FC","matches":7,"wins":4,"losses":3,"draws":0,"goals":6,"assists":4,"shots":24,"shotsontarget":15,"passes":230,"passescompleted":120,"interceptions":95,"saves":60,"fouls":0,"yellowcards":0,"redcards":0,"owngoals":1,"offsides":3,"distancecovered":3462.8571428571427,"possession":8.428571428571429,"corners":2,"throwins":5,"penalties":0,"freekicks":1,"tackles":23,"tacklescompleted":3,"foulssuffered":1,"savescaught":50,"goalkicks":32,"goalsconceded":25,"secondsplayed":39719,"keypasses":0,"chancescreated":0,"secondassists":0},{"_id":"STEAM_0:0:170711893","name":"Cianuro'","steamID":"STEAM_0:0:170711893","team":"Colchester United FC","matches":11,"wins":8,"losses":3,"draws":0,"goals":7,"assists":3,"shots":32,"shotsontarget":23,"passes":270,"passescompleted":131,"interceptions":109,"saves":3,"fouls":0,"yellowcards":0,"redcards":0,"owngoals":0,"offsides":6,"distancecovered":5672.636363636364,"possession":7.454545454545454,"corners":4,"throwins":32,"penalties":0,"freekicks":2,"tackles":23,"tacklescompleted":2,"foulssuffered":0,"savescaught":3,"goalkicks":2,"goalsconceded":2,"secondsplayed":47903,"keypasses":0,"chancescreated":0,"secondassists":0},{"_id":"STEAM_0:1:36779496","name":"David","steamID":"STEAM_0:1:36779496","team":"Colchester United FC","matches":14,"wins":9,"losses":5,"draws":0,"goals":28,"assists":8,"shots":87,"shotsontarget":64,"passes":369,"passescompleted":205,"interceptions":86,"saves":20,"fouls":1,"yellowcards":1,"redcards":0,"owngoals":0,"offsides":8,"distancecovered":6352.428571428572,"possession":8.571428571428571,"corners":12,"throwins":25,"penalties":1,"freekicks":5,"tackles":34,"tacklescompleted":3,"foulssuffered":3,"savescaught":16,"goalkicks":15,"goalsconceded":17,"secondsplayed":74913,"keypasses":0,"chancescreated":0,"secondassists":0},{"_id":"STEAM_0:1:34660117","name":"Freddie","steamID":"STEAM_0:1:34660117","team":"Colchester United FC","matches":15,"wins":9,"losses":6,"draws":0,"goals":23,"assists":19,"shots":96,"shotsontarget":67,"passes":471,"passescompleted":287,"interceptions":126,"saves":0,"fouls":6,"yellowcards":6,"redcards":2,"owngoals":0,"offsides":6,"distancecovered":7635.533333333334,"possession":16.133333333333333,"corners":20,"throwins":32,"penalties":0,"freekicks":11,"tackles":81,"tacklescompleted":17,"foulssuffered":6,"savescaught":0,"goalkicks":0,"goalsconceded":0,"secondsplayed":83112,"keypasses":0,"chancescreated":0,"secondassists":0},{"_id":"STEAM_0:0:157502073","name":"Gabito","steamID":"STEAM_0:0:157502073","team":"Colchester United FC","matches":14,"wins":9,"losses":5,"draws":0,"goals":5,"assists":3,"shots":26,"shotsontarget":18,"passes":461,"passescompleted":300,"interceptions":231,"saves":11,"fouls":2,"yellowcards":0,"redcards":0,"owngoals":0,"offsides":0,"distancecovered":6216.571428571428,"possession":10.928571428571429,"corners":2,"throwins":36,"penalties":0,"freekicks":4,"tackles":31,"tacklescompleted":5,"foulssuffered":4,"savescaught":6,"goalkicks":10,"goalsconceded":8,"secondsplayed":117407,"keypasses":0,"chancescreated":0,"secondassists":0},{"_id":"STEAM_0:1:44654056","name":"Palta","steamID":"STEAM_0:1:44654056","team":"Colchester United FC","matches":9,"wins":6,"losses":3,"draws":0,"goals":0,"assists":1,"shots":0,"shotsontarget":0,"passes":230,"passescompleted":164,"interceptions":87,"saves":67,"fouls":0,"yellowcards":0,"redcards":0,"owngoals":0,"offsides":0,"distancecovered":1472.2222222222222,"possession":3.4444444444444446,"corners":0,"throwins":0,"penalties":0,"freekicks":1,"tackles":1,"tacklescompleted":0,"foulssuffered":0,"savescaught":49,"goalkicks":89,"goalsconceded":51,"secondsplayed":51294,"keypasses":0,"chancescreated":0,"secondassists":0},{"_id":"STEAM_0:1:55874138","name":"Reus","steamID":"STEAM_0:1:55874138","team":"Colchester United FC","matches":2,"wins":2,"losses":0,"draws":0,"goals":0,"assists":0,"shots":2,"shotsontarget":2,"passes":52,"passescompleted":25,"interceptions":25,"saves":0,"fouls":0,"yellowcards":0,"redcards":0,"owngoals":0,"offsides":0,"distancecovered":7360,"possession":7.5,"corners":0,"throwins":6,"penalties":0,"freekicks":0,"tackles":8,"tacklescompleted":2,"foulssuffered":0,"savescaught":0,"goalkicks":0,"goalsconceded":0,"secondsplayed":10858,"keypasses":0,"chancescreated":0,"secondassists":0},{"_id":"STEAM_0:0:207510815","name":"SickGuy","steamID":"STEAM_0:0:207510815","team":"Colchester United FC","matches":5,"wins":1,"losses":4,"draws":0,"goals":0,"assists":0,"shots":1,"shotsontarget":0,"passes":39,"passescompleted":22,"interceptions":26,"saves":0,"fouls":0,"yellowcards":0,"redcards":0,"owngoals":1,"offsides":1,"distancecovered":5359.6,"possession":2.6,"corners":0,"throwins":14,"penalties":0,"freekicks":1,"tackles":5,"tacklescompleted":0,"foulssuffered":1,"savescaught":0,"goalkicks":0,"goalsconceded":0,"secondsplayed":33839,"keypasses":0,"chancescreated":0,"secondassists":0},{"_id":"STEAM_0:0:419151897","name":"el seda","steamID":"STEAM_0:0:419151897","team":"Colchester United FC","matches":6,"wins":3,"losses":3,"draws":0,"goals":1,"assists":0,"shots":6,"shotsontarget":4,"passes":52,"passescompleted":26,"interceptions":13,"saves":0,"fouls":3,"yellowcards":2,"redcards":1,"owngoals":0,"offsides":0,"distancecovered":4446.333333333333,"possession":3.5,"corners":1,"throwins":11,"penalties":0,"freekicks":0,"tackles":50,"tacklescompleted":2,"foulssuffered":0,"savescaught":0,"goalkicks":0,"goalsconceded":0,"secondsplayed":62472,"keypasses":0,"chancescreated":0,"secondassists":0},{"_id":"STEAM_0:1:103282943","name":"Burruchaga","steamID":"STEAM_0:1:103282943","team":"Defensores Del Bidon","matches":5,"wins":2,"losses":3,"draws":0,"goals":0,"assists":1,"shots":5,"shotsontarget":3,"passes":137,"passescompleted":55,"interceptions":81,"saves":0,"fouls":3,"yellowcards":3,"redcards":1,"owngoals":0,"offsides":0,"distancecovered":5914.2,"possession":9.4,"corners":1,"throwins":18,"penalties":0,"freekicks":8,"tackles":26,"tacklescompleted":7,"foulssuffered":4,"savescaught":0,"goalkicks":0,"goalsconceded":0,"secondsplayed":23701,"keypasses":0,"chancescreated":0,"secondassists":0},{"_id":"STEAM_0:0:155558536","name":"Dario Benedetto","steamID":"STEAM_0:0:155558536","team":"Defensores Del Bidon","matches":8,"wins":2,"losses":6,"draws":0,"goals":7,"assists":0,"shots":31,"shotsontarget":20,"passes":115,"passescompleted":43,"interceptions":17,"saves":0,"fouls":2,"yellowcards":0,"redcards":0,"owngoals":0,"offsides":1,"distancecovered":5217.375,"possession":5.25,"corners":2,"throwins":14,"penalties":0,"freekicks":4,"tackles":69,"tacklescompleted":7,"foulssuffered":2,"savescaught":0,"goalkicks":0,"goalsconceded":0,"secondsplayed":56063,"keypasses":0,"chancescreated":0,"secondassists":0},{"_id":"STEAM_0:1:198352224","name":"EL BOCHA","steamID":"STEAM_0:1:198352224","team":"Defensores Del Bidon","matches":4,"wins":1,"losses":3,"draws":0,"goals":1,"assists":0,"shots":6,"shotsontarget":5,"passes":50,"passescompleted":21,"interceptions":19,"saves":0,"fouls":0,"yellowcards":0,"redcards":0,"owngoals":0,"offsides":2,"distancecovered":5452.25,"possession":5,"corners":1,"throwins":3,"penalties":0,"freekicks":3,"tackles":9,"tacklescompleted":0,"foulssuffered":2,"savescaught":0,"goalkicks":0,"goalsconceded":0,"secondsplayed":16013,"keypasses":0,"chancescreated":0,"secondassists":0},{"_id":"STEAM_0:0:246709140","name":"Enzo","steamID":"STEAM_0:0:246709140","team":"Defensores Del Bidon","matches":3,"wins":1,"losses":2,"draws":0,"goals":0,"assists":0,"shots":0,"shotsontarget":0,"passes":71,"passescompleted":33,"interceptions":15,"saves":26,"fouls":0,"yellowcards":0,"redcards":0,"owngoals":0,"offsides":0,"distancecovered":1387.3333333333333,"possession":5.333333333333333,"corners":0,"throwins":0,"penalties":0,"freekicks":2,"tackles":0,"tacklescompleted":0,"foulssuffered":0,"savescaught":13,"goalkicks":36,"goalsconceded":31,"secondsplayed":17265,"keypasses":0,"chancescreated":0,"secondassists":0},{"_id":"BOT","name":"KeeperBotAway","steamID":"BOT","team":"Defensores Del Bidon","matches":3,"wins":0,"losses":3,"draws":0,"goals":0,"assists":0,"shots":0,"shotsontarget":0,"passes":50,"passescompleted":11,"interceptions":4,"saves":22,"fouls":0,"yellowcards":0,"redcards":0,"owngoals":0,"offsides":0,"distancecovered":1088.6666666666667,"possession":2.6666666666666665,"corners":0,"throwins":0,"penalties":0,"freekicks":0,"tackles":0,"tacklescompleted":0,"foulssuffered":0,"savescaught":16,"goalkicks":28,"goalsconceded":8,"secondsplayed":5641,"keypasses":0,"chancescreated":0,"secondassists":0},{"_id":"STEAM_0:0:87965139","name":"Naran","steamID":"STEAM_0:0:87965139","team":"Defensores Del Bidon","matches":5,"wins":2,"losses":3,"draws":0,"goals":4,"assists":2,"shots":10,"shotsontarget":9,"passes":106,"passescompleted":55,"interceptions":40,"saves":0,"fouls":3,"yellowcards":1,"redcards":0,"owngoals":0,"offsides":0,"distancecovered":6038.2,"possession":6.2,"corners":0,"throwins":14,"penalties":0,"freekicks":2,"tackles":27,"tacklescompleted":4,"foulssuffered":0,"savescaught":0,"goalkicks":0,"goalsconceded":0,"secondsplayed":24609,"keypasses":0,"chancescreated":0,"secondassists":0},{"_id":"STEAM_0:1:245274134","name":"Benji Ice","steamID":"STEAM_0:1:245274134","team":"Defensores Del Doctor","matches":6,"wins":3,"losses":3,"draws":0,"goals":0,"assists":1,"shots":2,"shotsontarget":0,"passes":109,"passescompleted":52,"interceptions":45,"saves":31,"fouls":0,"yellowcards":0,"redcards":0,"owngoals":0,"offsides":0,"distancecovered":2570.3333333333335,"possession":3.6666666666666665,"corners":0,"throwins":0,"penalties":0,"freekicks":0,"tackles":0,"tacklescompleted":0,"foulssuffered":0,"savescaught":22,"goalkicks":34,"goalsconceded":17,"secondsplayed":76549,"keypasses":0,"chancescreated":0,"secondassists":0},{"_id":"STEAM_0:1:67981774","name":"Joakoxs#NvDantoyCuca","steamID":"STEAM_0:1:67981774","team":"Defensores Del Doctor","matches":18,"wins":8,"losses":10,"draws":0,"goals":6,"assists":5,"shots":58,"shotsontarget":36,"passes":556,"passescompleted":241,"interceptions":234,"saves":0,"fouls":2,"yellowcards":2,"redcards":0,"owngoals":0,"offsides":1,"distancecovered":6090.611111111111,"possession":7.555555555555555,"corners":1,"throwins":91,"penalties":0,"freekicks":5,"tackles":70,"tacklescompleted":9,"foulssuffered":2,"savescaught":0,"goalkicks":1,"goalsconceded":0,"secondsplayed":136413,"keypasses":0,"chancescreated":0,"secondassists":0},{"_id":"STEAM_0:1:185950898","name":"Lukitas","steamID":"STEAM_0:1:185950898","team":"Defensores Del Doctor","matches":5,"wins":2,"losses":3,"draws":0,"goals":2,"assists":0,"shots":2,"shotsontarget":2,"passes":54,"passescompleted":21,"interceptions":30,"saves":6,"fouls":2,"yellowcards":1,"redcards":0,"owngoals":1,"offsides":0,"distancecovered":2362.2,"possession":3,"corners":0,"throwins":7,"penalties":1,"freekicks":1,"tackles":10,"tacklescompleted":3,"foulssuffered":0,"savescaught":5,"goalkicks":4,"goalsconceded":4,"secondsplayed":11652,"keypasses":0,"chancescreated":0,"secondassists":0},{"_id":"STEAM_0:0:76340856","name":"Luqita#Cambiemos","steamID":"STEAM_0:0:76340856","team":"Defensores Del Doctor","matches":16,"wins":5,"losses":10,"draws":1,"goals":34,"assists":11,"shots":90,"shotsontarget":66,"passes":446,"passescompleted":257,"interceptions":164,"saves":0,"fouls":4,"yellowcards":3,"redcards":0,"owngoals":0,"offsides":12,"distancecovered":6095.5625,"possession":12.1875,"corners":6,"throwins":40,"penalties":1,"freekicks":7,"tackles":78,"tacklescompleted":20,"foulssuffered":5,"savescaught":0,"goalkicks":1,"goalsconceded":0,"secondsplayed":147719,"keypasses":0,"chancescreated":0,"secondassists":0},{"_id":"STEAM_0:1:48359313","name":"Potatuzz #NvDantoyCuca","steamID":"STEAM_0:1:48359313","team":"Defensores Del Doctor","matches":17,"wins":7,"losses":10,"draws":0,"goals":27,"assists":5,"shots":111,"shotsontarget":77,"passes":338,"passescompleted":154,"interceptions":74,"saves":1,"fouls":10,"yellowcards":9,"redcards":1,"owngoals":0,"offsides":18,"distancecovered":5648.941176470588,"possession":7.411764705882353,"corners":24,"throwins":37,"penalties":2,"freekicks":11,"tackles":84,"tacklescompleted":8,"foulssuffered":10,"savescaught":0,"goalkicks":1,"goalsconceded":1,"secondsplayed":126839,"keypasses":0,"chancescreated":0,"secondassists":0},{"_id":"STEAM_0:1:198516942","name":"TuViejaxdd","steamID":"STEAM_0:1:198516942","team":"Defensores Del Doctor","matches":8,"wins":3,"losses":5,"draws":0,"goals":0,"assists":0,"shots":4,"shotsontarget":3,"passes":65,"passescompleted":24,"interceptions":31,"saves":0,"fouls":0,"yellowcards":0,"redcards":0,"owngoals":0,"offsides":0,"distancecovered":2675.875,"possession":2.5,"corners":0,"throwins":4,"penalties":0,"freekicks":2,"tackles":8,"tacklescompleted":2,"foulssuffered":0,"savescaught":0,"goalkicks":1,"goalsconceded":0,"secondsplayed":16811,"keypasses":0,"chancescreated":0,"secondassists":0},{"_id":"STEAM_0:0:245137691","name":"TumorTadela #JoakoCap","steamID":"STEAM_0:0:245137691","team":"Defensores Del Doctor","matches":13,"wins":5,"losses":8,"draws":0,"goals":0,"assists":2,"shots":8,"shotsontarget":0,"passes":315,"passescompleted":166,"interceptions":80,"saves":112,"fouls":0,"yellowcards":0,"redcards":0,"owngoals":0,"offsides":0,"distancecovered":2751.3076923076924,"possession":5.3076923076923075,"corners":0,"throwins":0,"penalties":0,"freekicks":0,"tackles":1,"tacklescompleted":0,"foulssuffered":0,"savescaught":81,"goalkicks":99,"goalsconceded":53,"secondsplayed":68601,"keypasses":0,"chancescreated":0,"secondassists":0},{"_id":"STEAM_0:1:203419491","name":"Zerix","steamID":"STEAM_0:1:203419491","team":"Defensores Del Doctor","matches":5,"wins":1,"losses":4,"draws":0,"goals":4,"assists":0,"shots":24,"shotsontarget":19,"passes":76,"passescompleted":27,"interceptions":46,"saves":0,"fouls":2,"yellowcards":2,"redcards":0,"owngoals":0,"offsides":0,"distancecovered":4562.2,"possession":6,"corners":3,"throwins":6,"penalties":0,"freekicks":4,"tackles":29,"tacklescompleted":3,"foulssuffered":3,"savescaught":0,"goalkicks":0,"goalsconceded":0,"secondsplayed":17737,"keypasses":0,"chancescreated":0,"secondassists":0},{"_id":"STEAM_0:1:128106997","name":"Zerix","steamID":"STEAM_0:1:128106997","team":"Defensores Del Doctor","matches":11,"wins":7,"losses":4,"draws":0,"goals":5,"assists":12,"shots":40,"shotsontarget":28,"passes":283,"passescompleted":141,"interceptions":127,"saves":0,"fouls":2,"yellowcards":1,"redcards":0,"owngoals":0,"offsides":2,"distancecovered":6215.727272727273,"possession":9.090909090909092,"corners":2,"throwins":28,"penalties":0,"freekicks":6,"tackles":30,"tacklescompleted":6,"foulssuffered":1,"savescaught":0,"goalkicks":0,"goalsconceded":0,"secondsplayed":103933,"keypasses":0,"chancescreated":0,"secondassists":0},{"_id":"STEAM_0:0:214464024","name":"cuca","steamID":"STEAM_0:0:214464024","team":"Defensores Del Doctor","matches":11,"wins":3,"losses":7,"draws":1,"goals":10,"assists":2,"shots":42,"shotsontarget":29,"passes":222,"passescompleted":116,"interceptions":40,"saves":0,"fouls":2,"yellowcards":1,"redcards":1,"owngoals":0,"offsides":3,"distancecovered":4457.727272727273,"possession":8.363636363636363,"corners":4,"throwins":10,"penalties":0,"freekicks":2,"tackles":25,"tacklescompleted":4,"foulssuffered":0,"savescaught":0,"goalkicks":0,"goalsconceded":0,"secondsplayed":79206,"keypasses":0,"chancescreated":0,"secondassists":0},{"_id":"STEAM_0:0:98901724","name":"danto poxyran","steamID":"STEAM_0:0:98901724","team":"Defensores Del Doctor","matches":17,"wins":9,"losses":8,"draws":0,"goals":8,"assists":10,"shots":85,"shotsontarget":57,"passes":465,"passescompleted":165,"interceptions":274,"saves":0,"fouls":2,"yellowcards":1,"redcards":1,"owngoals":0,"offsides":0,"distancecovered":6461.588235294118,"possession":7.882352941176471,"corners":9,"throwins":81,"penalties":0,"freekicks":5,"tackles":25,"tacklescompleted":5,"foulssuffered":0,"savescaught":0,"goalkicks":0,"goalsconceded":0,"secondsplayed":83909,"keypasses":0,"chancescreated":0,"secondassists":0},{"_id":"STEAM_0:0:385653791","name":"Axs","steamID":"STEAM_0:0:385653791","team":"Jubilados","matches":4,"wins":1,"losses":3,"draws":0,"goals":0,"assists":0,"shots":1,"shotsontarget":0,"passes":105,"passescompleted":79,"interceptions":40,"saves":43,"fouls":0,"yellowcards":0,"redcards":0,"owngoals":0,"offsides":0,"distancecovered":3293,"possession":4,"corners":0,"throwins":0,"penalties":0,"freekicks":0,"tackles":0,"tacklescompleted":0,"foulssuffered":0,"savescaught":35,"goalkicks":28,"goalsconceded":27,"secondsplayed":61924,"keypasses":0,"chancescreated":0,"secondassists":0},{"_id":"STEAM_0:1:55716910","name":"Axs","steamID":"STEAM_0:1:55716910","team":"Jubilados","matches":2,"wins":1,"losses":1,"draws":0,"goals":0,"assists":2,"shots":0,"shotsontarget":0,"passes":45,"passescompleted":39,"interceptions":18,"saves":18,"fouls":0,"yellowcards":0,"redcards":0,"owngoals":0,"offsides":0,"distancecovered":3883,"possession":4,"corners":0,"throwins":0,"penalties":0,"freekicks":0,"tackles":0,"tacklescompleted":0,"foulssuffered":0,"savescaught":15,"goalkicks":12,"goalsconceded":12,"secondsplayed":11454,"keypasses":0,"chancescreated":0,"secondassists":0},{"_id":"STEAM_0:1:32216071","name":"Casana.","steamID":"STEAM_0:1:32216071","team":"Jubilados","matches":15,"wins":6,"losses":9,"draws":0,"goals":12,"assists":11,"shots":51,"shotsontarget":34,"passes":610,"passescompleted":334,"interceptions":180,"saves":0,"fouls":8,"yellowcards":5,"redcards":1,"owngoals":0,"offsides":0,"distancecovered":6822.333333333333,"possession":14.533333333333333,"corners":7,"throwins":64,"penalties":0,"freekicks":9,"tackles":55,"tacklescompleted":10,"foulssuffered":3,"savescaught":0,"goalkicks":0,"goalsconceded":0,"secondsplayed":120974,"keypasses":0,"chancescreated":0,"secondassists":0},{"_id":"STEAM_0:0:211587437","name":"Eliam","steamID":"STEAM_0:0:211587437","team":"Jubilados","matches":8,"wins":3,"losses":5,"draws":0,"goals":4,"assists":0,"shots":27,"shotsontarget":21,"passes":76,"passescompleted":35,"interceptions":28,"saves":0,"fouls":1,"yellowcards":1,"redcards":0,"owngoals":0,"offsides":0,"distancecovered":4109,"possession":3.875,"corners":3,"throwins":14,"penalties":0,"freekicks":2,"tackles":6,"tacklescompleted":0,"foulssuffered":1,"savescaught":0,"goalkicks":0,"goalsconceded":0,"secondsplayed":24675,"keypasses":0,"chancescreated":0,"secondassists":0},{"_id":"STEAM_0:0:41702500","name":"Fortu","steamID":"STEAM_0:0:41702500","team":"Jubilados","matches":12,"wins":7,"losses":5,"draws":0,"goals":6,"assists":5,"shots":33,"shotsontarget":29,"passes":453,"passescompleted":243,"interceptions":182,"saves":0,"fouls":6,"yellowcards":6,"redcards":0,"owngoals":0,"offsides":1,"distancecovered":6581.833333333333,"possession":10.75,"corners":2,"throwins":72,"penalties":0,"freekicks":6,"tackles":40,"tacklescompleted":5,"foulssuffered":0,"savescaught":0,"goalkicks":0,"goalsconceded":0,"secondsplayed":64112,"keypasses":0,"chancescreated":0,"secondassists":0},{"_id":"STEAM_0:1:32295184","name":"Hasbi","steamID":"STEAM_0:1:32295184","team":"Jubilados","matches":17,"wins":8,"losses":9,"draws":0,"goals":37,"assists":6,"shots":146,"shotsontarget":104,"passes":390,"passescompleted":225,"interceptions":69,"saves":2,"fouls":4,"yellowcards":3,"redcards":0,"owngoals":0,"offsides":9,"distancecovered":6785.235294117647,"possession":9.705882352941176,"corners":17,"throwins":28,"penalties":0,"freekicks":13,"tackles":52,"tacklescompleted":5,"foulssuffered":8,"savescaught":2,"goalkicks":0,"goalsconceded":0,"secondsplayed":126415,"keypasses":0,"chancescreated":0,"secondassists":0},{"_id":"STEAM_0:0:79679536","name":"Legui","steamID":"STEAM_0:0:79679536","team":"Jubilados","matches":3,"wins":2,"losses":1,"draws":0,"goals":1,"assists":0,"shots":2,"shotsontarget":1,"passes":47,"passescompleted":24,"interceptions":11,"saves":0,"fouls":0,"yellowcards":0,"redcards":0,"owngoals":0,"offsides":3,"distancecovered":5733.333333333333,"possession":4.666666666666667,"corners":1,"throwins":7,"penalties":0,"freekicks":0,"tackles":5,"tacklescompleted":1,"foulssuffered":0,"savescaught":0,"goalkicks":0,"goalsconceded":0,"secondsplayed":55011,"keypasses":0,"chancescreated":0,"secondassists":0},{"_id":"STEAM_0:1:176765952","name":"Mariano","steamID":"STEAM_0:1:176765952","team":"Jubilados","matches":10,"wins":4,"losses":6,"draws":0,"goals":2,"assists":3,"shots":30,"shotsontarget":22,"passes":304,"passescompleted":174,"interceptions":126,"saves":0,"fouls":2,"yellowcards":1,"redcards":0,"owngoals":0,"offsides":2,"distancecovered":6256.7,"possession":8.8,"corners":3,"throwins":33,"penalties":0,"freekicks":3,"tackles":16,"tacklescompleted":1,"foulssuffered":0,"savescaught":0,"goalkicks":0,"goalsconceded":0,"secondsplayed":92981,"keypasses":0,"chancescreated":0,"secondassists":0},{"_id":"STEAM_0:1:54458707","name":"Pelusa","steamID":"STEAM_0:1:54458707","team":"Jubilados","matches":4,"wins":1,"losses":3,"draws":0,"goals":0,"assists":1,"shots":1,"shotsontarget":0,"passes":118,"passescompleted":87,"interceptions":44,"saves":36,"fouls":0,"yellowcards":0,"redcards":0,"owngoals":0,"offsides":0,"distancecovered":3404,"possession":5,"corners":0,"throwins":0,"penalties":0,"freekicks":0,"tackles":0,"tacklescompleted":0,"foulssuffered":0,"savescaught":33,"goalkicks":34,"goalsconceded":20,"secondsplayed":19673,"keypasses":0,"chancescreated":0,"secondassists":0},{"_id":"STEAM_0:1:77687043","name":"Baba","steamID":"STEAM_0:1:77687043","team":"Just Fragging","matches":18,"wins":12,"losses":5,"draws":1,"goals":3,"assists":5,"shots":46,"shotsontarget":31,"passes":797,"passescompleted":471,"interceptions":262,"saves":0,"fouls":3,"yellowcards":2,"redcards":1,"owngoals":0,"offsides":0,"distancecovered":7108.722222222223,"possession":12.555555555555555,"corners":1,"throwins":89,"penalties":0,"freekicks":11,"tackles":43,"tacklescompleted":12,"foulssuffered":2,"savescaught":0,"goalkicks":0,"goalsconceded":0,"secondsplayed":143621,"keypasses":0,"chancescreated":0,"secondassists":0},{"_id":"STEAM_0:1:46153462","name":"CaballSampaoli","steamID":"STEAM_0:1:46153462","team":"Just Fragging","matches":15,"wins":11,"losses":4,"draws":0,"goals":11,"assists":3,"shots":44,"shotsontarget":37,"passes":204,"passescompleted":104,"interceptions":46,"saves":0,"fouls":1,"yellowcards":1,"redcards":0,"owngoals":0,"offsides":7,"distancecovered":4837.666666666667,"possession":5.666666666666667,"corners":4,"throwins":21,"penalties":0,"freekicks":5,"tackles":65,"tacklescompleted":4,"foulssuffered":1,"savescaught":0,"goalkicks":0,"goalsconceded":0,"secondsplayed":52533,"keypasses":0,"chancescreated":0,"secondassists":0},{"_id":"STEAM_0:1:59420231","name":"HR","steamID":"STEAM_0:1:59420231","team":"Just Fragging","matches":6,"wins":3,"losses":3,"draws":0,"goals":4,"assists":1,"shots":14,"shotsontarget":9,"passes":85,"passescompleted":35,"interceptions":26,"saves":0,"fouls":0,"yellowcards":0,"redcards":0,"owngoals":0,"offsides":1,"distancecovered":4478.666666666667,"possession":3,"corners":4,"throwins":10,"penalties":0,"freekicks":0,"tackles":0,"tacklescompleted":0,"foulssuffered":0,"savescaught":0,"goalkicks":0,"goalsconceded":0,"secondsplayed":62145,"keypasses":0,"chancescreated":0,"secondassists":0},{"_id":"STEAM_0:0:87697113","name":"LISO","steamID":"STEAM_0:0:87697113","team":"Just Fragging","matches":10,"wins":5,"losses":4,"draws":1,"goals":0,"assists":1,"shots":20,"shotsontarget":12,"passes":222,"passescompleted":134,"interceptions":33,"saves":0,"fouls":2,"yellowcards":1,"redcards":0,"owngoals":0,"offsides":2,"distancecovered":6457.2,"possession":6,"corners":7,"throwins":32,"penalties":0,"freekicks":4,"tackles":4,"tacklescompleted":1,"foulssuffered":0,"savescaught":0,"goalkicks":0,"goalsconceded":0,"secondsplayed":143635,"keypasses":0,"chancescreated":0,"secondassists":0},{"_id":"STEAM_0:0:42043307","name":"PEPSI WEISSTROYER","steamID":"STEAM_0:0:42043307","team":"Just Fragging","matches":15,"wins":9,"losses":4,"draws":2,"goals":6,"assists":8,"shots":47,"shotsontarget":33,"passes":600,"passescompleted":323,"interceptions":179,"saves":0,"fouls":8,"yellowcards":8,"redcards":1,"owngoals":0,"offsides":0,"distancecovered":5979.666666666667,"possession":11.866666666666667,"corners":3,"throwins":74,"penalties":0,"freekicks":7,"tackles":45,"tacklescompleted":12,"foulssuffered":4,"savescaught":0,"goalkicks":1,"goalsconceded":0,"secondsplayed":69346,"keypasses":0,"chancescreated":0,"secondassists":0},{"_id":"STEAM_0:1:54137383","name":"Rawix","steamID":"STEAM_0:1:54137383","team":"Just Fragging","matches":10,"wins":8,"losses":2,"draws":0,"goals":9,"assists":2,"shots":31,"shotsontarget":25,"passes":184,"passescompleted":127,"interceptions":27,"saves":0,"fouls":3,"yellowcards":3,"redcards":1,"owngoals":0,"offsides":8,"distancecovered":4490.6,"possession":5.7,"corners":6,"throwins":9,"penalties":0,"freekicks":5,"tackles":43,"tacklescompleted":5,"foulssuffered":2,"savescaught":0,"goalkicks":0,"goalsconceded":0,"secondsplayed":33019,"keypasses":0,"chancescreated":0,"secondassists":0},{"_id":"STEAM_0:1:36492034","name":"Skay","steamID":"STEAM_0:1:36492034","team":"Just Fragging","matches":13,"wins":7,"losses":5,"draws":1,"goals":4,"assists":9,"shots":21,"shotsontarget":16,"passes":567,"passescompleted":240,"interceptions":178,"saves":0,"fouls":0,"yellowcards":0,"redcards":0,"owngoals":0,"offsides":0,"distancecovered":7001.307692307692,"possession":11.23076923076923,"corners":3,"throwins":63,"penalties":1,"freekicks":5,"tackles":32,"tacklescompleted":8,"foulssuffered":3,"savescaught":0,"goalkicks":1,"goalsconceded":0,"secondsplayed":111163,"keypasses":0,"chancescreated":0,"secondassists":0},{"_id":"STEAM_0:0:445048118","name":"Syne","steamID":"STEAM_0:0:445048118","team":"Just Fragging","matches":10,"wins":6,"losses":4,"draws":0,"goals":2,"assists":2,"shots":16,"shotsontarget":10,"passes":78,"passescompleted":57,"interceptions":17,"saves":0,"fouls":2,"yellowcards":2,"redcards":0,"owngoals":0,"offsides":2,"distancecovered":2854.2,"possession":3.1,"corners":2,"throwins":11,"penalties":0,"freekicks":5,"tackles":18,"tacklescompleted":1,"foulssuffered":4,"savescaught":0,"goalkicks":0,"goalsconceded":0,"secondsplayed":22414,"keypasses":0,"chancescreated":0,"secondassists":0},{"_id":"STEAM_0:0:106863957","name":"Trx","steamID":"STEAM_0:0:106863957","team":"Just Fragging","matches":18,"wins":12,"losses":5,"draws":1,"goals":1,"assists":1,"shots":10,"shotsontarget":3,"passes":638,"passescompleted":466,"interceptions":241,"saves":161,"fouls":0,"yellowcards":0,"redcards":0,"owngoals":1,"offsides":0,"distancecovered":4071.8888888888887,"possession":6.388888888888889,"corners":0,"throwins":0,"penalties":0,"freekicks":2,"tackles":6,"tacklescompleted":0,"foulssuffered":0,"savescaught":134,"goalkicks":142,"goalsconceded":63,"secondsplayed":142397,"keypasses":0,"chancescreated":0,"secondassists":0},{"_id":"STEAM_0:1:448563939","name":"Alim =D","steamID":"STEAM_0:1:448563939","team":"Los Halcones","matches":2,"wins":0,"losses":2,"draws":0,"goals":0,"assists":0,"shots":1,"shotsontarget":0,"passes":35,"passescompleted":23,"interceptions":15,"saves":0,"fouls":0,"yellowcards":0,"redcards":0,"owngoals":0,"offsides":0,"distancecovered":4191,"possession":5,"corners":0,"throwins":4,"penalties":0,"freekicks":0,"tackles":0,"tacklescompleted":0,"foulssuffered":0,"savescaught":0,"goalkicks":0,"goalsconceded":0,"secondsplayed":59365,"keypasses":0,"chancescreated":0,"secondassists":0},{"_id":"STEAM_0:0:152914349","name":"KariusB","steamID":"STEAM_0:0:152914349","team":"Los Halcones","matches":6,"wins":2,"losses":4,"draws":0,"goals":5,"assists":2,"shots":30,"shotsontarget":18,"passes":136,"passescompleted":71,"interceptions":51,"saves":0,"fouls":2,"yellowcards":1,"redcards":1,"owngoals":0,"offsides":2,"distancecovered":6061.833333333333,"possession":9.5,"corners":8,"throwins":18,"penalties":0,"freekicks":3,"tackles":35,"tacklescompleted":10,"foulssuffered":1,"savescaught":0,"goalkicks":0,"goalsconceded":0,"secondsplayed":79532,"keypasses":0,"chancescreated":0,"secondassists":0},{"_id":"STEAM_0:1:200525073","name":"Magma","steamID":"STEAM_0:1:200525073","team":"Los Halcones","matches":1,"wins":1,"losses":0,"draws":0,"goals":6,"assists":0,"shots":14,"shotsontarget":14,"passes":16,"passescompleted":8,"interceptions":8,"saves":0,"fouls":1,"yellowcards":1,"redcards":0,"owngoals":0,"offsides":2,"distancecovered":7595,"possession":9,"corners":0,"throwins":4,"penalties":0,"freekicks":1,"tackles":3,"tacklescompleted":0,"foulssuffered":1,"savescaught":0,"goalkicks":0,"goalsconceded":0,"secondsplayed":5647,"keypasses":0,"chancescreated":0,"secondassists":0},{"_id":"STEAM_0:0:79180934","name":"Mayttek","steamID":"STEAM_0:0:79180934","team":"Los Halcones","matches":1,"wins":0,"losses":1,"draws":0,"goals":0,"assists":1,"shots":0,"shotsontarget":0,"passes":26,"passescompleted":18,"interceptions":11,"saves":9,"fouls":0,"yellowcards":0,"redcards":0,"owngoals":0,"offsides":0,"distancecovered":1365,"possession":4,"corners":0,"throwins":0,"penalties":0,"freekicks":0,"tackles":0,"tacklescompleted":0,"foulssuffered":0,"savescaught":7,"goalkicks":8,"goalsconceded":5,"secondsplayed":5700,"keypasses":0,"chancescreated":0,"secondassists":0},{"_id":"STEAM_0:1:43091671","name":"Ezetomil","steamID":"STEAM_0:1:43091671","team":"MEIWA","matches":15,"wins":7,"losses":8,"draws":0,"goals":5,"assists":7,"shots":26,"shotsontarget":17,"passes":427,"passescompleted":236,"interceptions":173,"saves":0,"fouls":3,"yellowcards":3,"redcards":0,"owngoals":0,"offsides":1,"distancecovered":6470.266666666666,"possession":8.866666666666667,"corners":7,"throwins":72,"penalties":0,"freekicks":5,"tackles":19,"tacklescompleted":0,"foulssuffered":2,"savescaught":0,"goalkicks":0,"goalsconceded":0,"secondsplayed":87616,"keypasses":0,"chancescreated":0,"secondassists":0},{"_id":"STEAM_0:0:434550252","name":"Gonza","steamID":"STEAM_0:0:434550252","team":"MEIWA","matches":3,"wins":1,"losses":2,"draws":0,"goals":2,"assists":2,"shots":10,"shotsontarget":9,"passes":58,"passescompleted":27,"interceptions":21,"saves":0,"fouls":2,"yellowcards":2,"redcards":0,"owngoals":0,"offsides":2,"distancecovered":5118.666666666667,"possession":7,"corners":3,"throwins":6,"penalties":0,"freekicks":2,"tackles":27,"tacklescompleted":6,"foulssuffered":0,"savescaught":0,"goalkicks":0,"goalsconceded":0,"secondsplayed":11703,"keypasses":0,"chancescreated":0,"secondassists":0},{"_id":"STEAM_0:1:18598047","name":"Indio","steamID":"STEAM_0:1:18598047","team":"MEIWA","matches":14,"wins":6,"losses":8,"draws":0,"goals":0,"assists":3,"shots":1,"shotsontarget":0,"passes":338,"passescompleted":199,"interceptions":94,"saves":122,"fouls":0,"yellowcards":0,"redcards":0,"owngoals":0,"offsides":0,"distancecovered":2043.7142857142858,"possession":4.285714285714286,"corners":0,"throwins":0,"penalties":0,"freekicks":0,"tackles":0,"tacklescompleted":0,"foulssuffered":0,"savescaught":95,"goalkicks":130,"goalsconceded":63,"secondsplayed":89194,"keypasses":0,"chancescreated":0,"secondassists":0},{"_id":"STEAM_0:0:143102885","name":"Ryok","steamID":"STEAM_0:0:143102885","team":"MEIWA","matches":15,"wins":10,"losses":5,"draws":0,"goals":1,"assists":9,"shots":15,"shotsontarget":8,"passes":374,"passescompleted":179,"interceptions":183,"saves":0,"fouls":1,"yellowcards":1,"redcards":0,"owngoals":0,"offsides":0,"distancecovered":6165.866666666667,"possession":7.933333333333334,"corners":3,"throwins":65,"penalties":0,"freekicks":6,"tackles":58,"tacklescompleted":14,"foulssuffered":2,"savescaught":0,"goalkicks":0,"goalsconceded":0,"secondsplayed":73331,"keypasses":0,"chancescreated":0,"secondassists":0},{"_id":"STEAM_0:1:3568830","name":"SADCHAVA","steamID":"STEAM_0:1:3568830","team":"MEIWA","matches":10,"wins":5,"losses":5,"draws":0,"goals":28,"assists":4,"shots":105,"shotsontarget":87,"passes":221,"passescompleted":97,"interceptions":61,"saves":0,"fouls":2,"yellowcards":2,"redcards":0,"owngoals":0,"offsides":5,"distancecovered":6788.3,"possession":14.7,"corners":17,"throwins":31,"penalties":0,"freekicks":8,"tackles":26,"tacklescompleted":2,"foulssuffered":5,"savescaught":0,"goalkicks":0,"goalsconceded":0,"secondsplayed":62988,"keypasses":0,"chancescreated":0,"secondassists":0},{"_id":"STEAM_0:1:116849518","name":"T O M","steamID":"STEAM_0:1:116849518","team":"MEIWA","matches":1,"wins":0,"losses":1,"draws":0,"goals":0,"assists":0,"shots":0,"shotsontarget":0,"passes":11,"passescompleted":7,"interceptions":3,"saves":0,"fouls":0,"yellowcards":0,"redcards":0,"owngoals":0,"offsides":0,"distancecovered":3981,"possession":3,"corners":0,"throwins":3,"penalties":0,"freekicks":0,"tackles":1,"tacklescompleted":0,"foulssuffered":0,"savescaught":0,"goalkicks":0,"goalsconceded":0,"secondsplayed":2884,"keypasses":0,"chancescreated":0,"secondassists":0},{"_id":"STEAM_0:1:442675911","name":"_Dybala_","steamID":"STEAM_0:1:442675911","team":"MEIWA","matches":11,"wins":5,"losses":6,"draws":0,"goals":22,"assists":4,"shots":76,"shotsontarget":56,"passes":184,"passescompleted":104,"interceptions":70,"saves":0,"fouls":2,"yellowcards":1,"redcards":0,"owngoals":0,"offsides":12,"distancecovered":5853.090909090909,"possession":9.636363636363637,"corners":15,"throwins":15,"penalties":1,"freekicks":4,"tackles":55,"tacklescompleted":10,"foulssuffered":4,"savescaught":0,"goalkicks":0,"goalsconceded":0,"secondsplayed":60649,"keypasses":0,"chancescreated":0,"secondassists":0},{"_id":"STEAM_0:0:56948573","name":"mbukke","steamID":"STEAM_0:0:56948573","team":"MEIWA","matches":13,"wins":5,"losses":8,"draws":0,"goals":8,"assists":3,"shots":40,"shotsontarget":23,"passes":355,"passescompleted":159,"interceptions":153,"saves":9,"fouls":2,"yellowcards":2,"redcards":0,"owngoals":0,"offsides":0,"distancecovered":5858,"possession":14.307692307692308,"corners":6,"throwins":42,"penalties":1,"freekicks":4,"tackles":54,"tacklescompleted":9,"foulssuffered":5,"savescaught":8,"goalkicks":4,"goalsconceded":0,"secondsplayed":128675,"keypasses":0,"chancescreated":0,"secondassists":0},{"_id":"STEAM_0:0:450580313","name":"Alim =D","steamID":"STEAM_0:0:450580313","team":"Meteors Gaming","matches":8,"wins":3,"losses":4,"draws":1,"goals":1,"assists":3,"shots":15,"shotsontarget":9,"passes":166,"passescompleted":96,"interceptions":103,"saves":0,"fouls":0,"yellowcards":0,"redcards":0,"owngoals":0,"offsides":0,"distancecovered":6436,"possession":6.25,"corners":1,"throwins":35,"penalties":0,"freekicks":1,"tackles":27,"tacklescompleted":7,"foulssuffered":0,"savescaught":0,"goalkicks":0,"goalsconceded":0,"secondsplayed":44510,"keypasses":0,"chancescreated":0,"secondassists":0},{"_id":"STEAM_0:1:23960874","name":"MartinnitraM","steamID":"STEAM_0:1:23960874","team":"Meteors Gaming","matches":12,"wins":5,"losses":6,"draws":1,"goals":2,"assists":3,"shots":22,"shotsontarget":14,"passes":227,"passescompleted":92,"interceptions":110,"saves":0,"fouls":0,"yellowcards":0,"redcards":0,"owngoals":0,"offsides":1,"distancecovered":6438.25,"possession":6.416666666666667,"corners":2,"throwins":33,"penalties":0,"freekicks":4,"tackles":42,"tacklescompleted":13,"foulssuffered":1,"savescaught":0,"goalkicks":1,"goalsconceded":0,"secondsplayed":56808,"keypasses":0,"chancescreated":0,"secondassists":0},{"_id":"STEAM_0:1:83759858","name":"Navarro","steamID":"STEAM_0:1:83759858","team":"Meteors Gaming","matches":2,"wins":0,"losses":1,"draws":1,"goals":0,"assists":0,"shots":0,"shotsontarget":0,"passes":16,"passescompleted":8,"interceptions":5,"saves":0,"fouls":0,"yellowcards":0,"redcards":0,"owngoals":0,"offsides":0,"distancecovered":4349.5,"possession":2,"corners":0,"throwins":4,"penalties":0,"freekicks":0,"tackles":0,"tacklescompleted":0,"foulssuffered":0,"savescaught":0,"goalkicks":0,"goalsconceded":0,"secondsplayed":6470,"keypasses":0,"chancescreated":0,"secondassists":0},{"_id":"STEAM_0:0:199329627","name":"Nicolai","steamID":"STEAM_0:0:199329627","team":"Meteors Gaming","matches":6,"wins":2,"losses":3,"draws":1,"goals":2,"assists":2,"shots":22,"shotsontarget":13,"passes":76,"passescompleted":43,"interceptions":19,"saves":1,"fouls":1,"yellowcards":1,"redcards":0,"owngoals":0,"offsides":2,"distancecovered":3509.1666666666665,"possession":4.333333333333333,"corners":5,"throwins":8,"penalties":0,"freekicks":0,"tackles":5,"tacklescompleted":0,"foulssuffered":0,"savescaught":1,"goalkicks":0,"goalsconceded":0,"secondsplayed":15358,"keypasses":0,"chancescreated":0,"secondassists":0},{"_id":"STEAM_0:1:102557870","name":"PEPE POMPIN","steamID":"STEAM_0:1:102557870","team":"Meteors Gaming","matches":11,"wins":3,"losses":7,"draws":1,"goals":0,"assists":1,"shots":6,"shotsontarget":0,"passes":325,"passescompleted":169,"interceptions":87,"saves":109,"fouls":0,"yellowcards":0,"redcards":0,"owngoals":0,"offsides":0,"distancecovered":1928.1818181818182,"possession":5.7272727272727275,"corners":0,"throwins":0,"penalties":0,"freekicks":2,"tackles":0,"tacklescompleted":0,"foulssuffered":0,"savescaught":86,"goalkicks":118,"goalsconceded":49,"secondsplayed":62486,"keypasses":0,"chancescreated":0,"secondassists":0},{"_id":"STEAM_0:1:41412728","name":"Pajaro","steamID":"STEAM_0:1:41412728","team":"Meteors Gaming","matches":11,"wins":3,"losses":7,"draws":1,"goals":12,"assists":6,"shots":65,"shotsontarget":43,"passes":340,"passescompleted":116,"interceptions":195,"saves":0,"fouls":2,"yellowcards":1,"redcards":0,"owngoals":0,"offsides":1,"distancecovered":7296.363636363636,"possession":13.363636363636363,"corners":3,"throwins":46,"penalties":0,"freekicks":9,"tackles":30,"tacklescompleted":9,"foulssuffered":3,"savescaught":0,"goalkicks":1,"goalsconceded":0,"secondsplayed":60831,"keypasses":0,"chancescreated":0,"secondassists":0},{"_id":"STEAM_0:1:210068895","name":"SiliconaEnLosPies","steamID":"STEAM_0:1:210068895","team":"Meteors Gaming","matches":10,"wins":1,"losses":7,"draws":2,"goals":15,"assists":8,"shots":45,"shotsontarget":36,"passes":223,"passescompleted":153,"interceptions":69,"saves":1,"fouls":3,"yellowcards":3,"redcards":0,"owngoals":0,"offsides":4,"distancecovered":6319.1,"possession":10.1,"corners":6,"throwins":22,"penalties":0,"freekicks":3,"tackles":16,"tacklescompleted":2,"foulssuffered":2,"savescaught":1,"goalkicks":0,"goalsconceded":0,"secondsplayed":48315,"keypasses":0,"chancescreated":0,"secondassists":0},{"_id":"STEAM_0:0:445518763","name":"SiliconaEnLosPies","steamID":"STEAM_0:0:445518763","team":"Meteors Gaming","matches":4,"wins":4,"losses":0,"draws":0,"goals":5,"assists":0,"shots":7,"shotsontarget":6,"passes":24,"passescompleted":16,"interceptions":11,"saves":0,"fouls":0,"yellowcards":0,"redcards":0,"owngoals":0,"offsides":1,"distancecovered":2588,"possession":3.5,"corners":1,"throwins":3,"penalties":0,"freekicks":0,"tackles":2,"tacklescompleted":1,"foulssuffered":0,"savescaught":0,"goalkicks":0,"goalsconceded":0,"secondsplayed":7793,"keypasses":0,"chancescreated":0,"secondassists":0},{"_id":"STEAM_0:0:58297993","name":"Willy","steamID":"STEAM_0:0:58297993","team":"Meteors Gaming","matches":18,"wins":9,"losses":7,"draws":2,"goals":27,"assists":12,"shots":116,"shotsontarget":89,"passes":492,"passescompleted":256,"interceptions":132,"saves":0,"fouls":4,"yellowcards":2,"redcards":0,"owngoals":0,"offsides":7,"distancecovered":7281.444444444444,"possession":10.833333333333334,"corners":22,"throwins":44,"penalties":1,"freekicks":9,"tackles":74,"tacklescompleted":13,"foulssuffered":7,"savescaught":0,"goalkicks":0,"goalsconceded":0,"secondsplayed":99003,"keypasses":0,"chancescreated":0,"secondassists":0},{"_id":"STEAM_0:1:185427236","name":"valencARc","steamID":"STEAM_0:1:185427236","team":"Meteors Gaming","matches":6,"wins":5,"losses":0,"draws":1,"goals":0,"assists":3,"shots":1,"shotsontarget":0,"passes":182,"passescompleted":86,"interceptions":63,"saves":33,"fouls":0,"yellowcards":0,"redcards":0,"owngoals":0,"offsides":0,"distancecovered":3197.1666666666665,"possession":6.5,"corners":0,"throwins":25,"penalties":0,"freekicks":1,"tackles":6,"tacklescompleted":0,"foulssuffered":0,"savescaught":20,"goalkicks":28,"goalsconceded":13,"secondsplayed":29624,"keypasses":0,"chancescreated":0,"secondassists":0},{"_id":"STEAM_0:0:104156683","name":"PatoCachalotes","steamID":"STEAM_0:0:104156683","team":"Musashi FC","matches":3,"wins":3,"losses":0,"draws":0,"goals":0,"assists":0,"shots":3,"shotsontarget":0,"passes":70,"passescompleted":32,"interceptions":24,"saves":20,"fouls":0,"yellowcards":0,"redcards":0,"owngoals":0,"offsides":0,"distancecovered":2628,"possession":4.666666666666667,"corners":0,"throwins":0,"penalties":0,"freekicks":2,"tackles":0,"tacklescompleted":0,"foulssuffered":0,"savescaught":16,"goalkicks":27,"goalsconceded":18,"secondsplayed":17153,"keypasses":0,"chancescreated":0,"secondassists":0},{"_id":"STEAM_0:1:94022148","name":"JuanmaCale10","steamID":"STEAM_0:1:94022148","team":"Painters United","matches":11,"wins":6,"losses":5,"draws":0,"goals":0,"assists":9,"shots":6,"shotsontarget":1,"passes":280,"passescompleted":190,"interceptions":96,"saves":104,"fouls":0,"yellowcards":0,"redcards":0,"owngoals":0,"offsides":0,"distancecovered":2972.181818181818,"possession":5.2727272727272725,"corners":0,"throwins":0,"penalties":0,"freekicks":0,"tackles":4,"tacklescompleted":0,"foulssuffered":0,"savescaught":87,"goalkicks":79,"goalsconceded":54,"secondsplayed":193597,"keypasses":0,"chancescreated":0,"secondassists":0},{"_id":"STEAM_0:1:41319820","name":"LUKKICHAN","steamID":"STEAM_0:1:41319820","team":"Painters United","matches":14,"wins":9,"losses":5,"draws":0,"goals":2,"assists":6,"shots":9,"shotsontarget":8,"passes":414,"passescompleted":219,"interceptions":175,"saves":22,"fouls":1,"yellowcards":1,"redcards":0,"owngoals":0,"offsides":0,"distancecovered":5655,"possession":7.5,"corners":0,"throwins":35,"penalties":0,"freekicks":1,"tackles":25,"tacklescompleted":5,"foulssuffered":0,"savescaught":17,"goalkicks":22,"goalsconceded":7,"secondsplayed":116434,"keypasses":0,"chancescreated":0,"secondassists":0},{"_id":"STEAM_0:1:123682146","name":"Neymar Jr","steamID":"STEAM_0:1:123682146","team":"Painters United","matches":14,"wins":8,"losses":6,"draws":0,"goals":44,"assists":11,"shots":95,"shotsontarget":72,"passes":362,"passescompleted":218,"interceptions":107,"saves":2,"fouls":11,"yellowcards":9,"redcards":1,"owngoals":0,"offsides":4,"distancecovered":5813.714285714285,"possession":14.857142857142858,"corners":21,"throwins":13,"penalties":1,"freekicks":12,"tackles":35,"tacklescompleted":3,"foulssuffered":10,"savescaught":1,"goalkicks":5,"goalsconceded":2,"secondsplayed":107565,"keypasses":0,"chancescreated":0,"secondassists":0},{"_id":"STEAM_0:0:126828334","name":"NicoRa23","steamID":"STEAM_0:0:126828334","team":"Painters United","matches":14,"wins":10,"losses":4,"draws":0,"goals":27,"assists":11,"shots":102,"shotsontarget":69,"passes":308,"passescompleted":170,"interceptions":95,"saves":0,"fouls":3,"yellowcards":3,"redcards":0,"owngoals":0,"offsides":2,"distancecovered":6255.071428571428,"possession":9.571428571428571,"corners":20,"throwins":40,"penalties":1,"freekicks":5,"tackles":53,"tacklescompleted":8,"foulssuffered":2,"savescaught":0,"goalkicks":0,"goalsconceded":0,"secondsplayed":109073,"keypasses":0,"chancescreated":0,"secondassists":0},{"_id":"STEAM_0:0:140615196","name":"Scocco","steamID":"STEAM_0:0:140615196","team":"Painters United","matches":12,"wins":9,"losses":3,"draws":0,"goals":6,"assists":4,"shots":20,"shotsontarget":18,"passes":382,"passescompleted":222,"interceptions":173,"saves":0,"fouls":2,"yellowcards":2,"redcards":0,"owngoals":0,"offsides":1,"distancecovered":6685.5,"possession":10.083333333333334,"corners":5,"throwins":55,"penalties":0,"freekicks":8,"tackles":37,"tacklescompleted":9,"foulssuffered":4,"savescaught":0,"goalkicks":1,"goalsconceded":0,"secondsplayed":106541,"keypasses":0,"chancescreated":0,"secondassists":0},{"_id":"STEAM_0:1:192575137","name":"kax","steamID":"STEAM_0:1:192575137","team":"Painters United","matches":14,"wins":8,"losses":6,"draws":0,"goals":14,"assists":5,"shots":73,"shotsontarget":50,"passes":215,"passescompleted":114,"interceptions":73,"saves":0,"fouls":0,"yellowcards":0,"redcards":0,"owngoals":0,"offsides":3,"distancecovered":4697.142857142857,"possession":7.214285714285714,"corners":6,"throwins":35,"penalties":1,"freekicks":1,"tackles":16,"tacklescompleted":2,"foulssuffered":1,"savescaught":0,"goalkicks":0,"goalsconceded":0,"secondsplayed":90913,"keypasses":0,"chancescreated":0,"secondassists":0},{"_id":"STEAM_0:1:221185704","name":"Alejo","steamID":"STEAM_0:1:221185704","team":"Santa Ana","matches":13,"wins":6,"losses":7,"draws":0,"goals":2,"assists":5,"shots":29,"shotsontarget":15,"passes":356,"passescompleted":168,"interceptions":145,"saves":0,"fouls":2,"yellowcards":2,"redcards":0,"owngoals":0,"offsides":3,"distancecovered":5846.153846153846,"possession":7.461538461538462,"corners":3,"throwins":49,"penalties":0,"freekicks":2,"tackles":19,"tacklescompleted":0,"foulssuffered":1,"savescaught":0,"goalkicks":1,"goalsconceded":0,"secondsplayed":115377,"keypasses":0,"chancescreated":0,"secondassists":0},{"_id":"STEAM_0:0:444629814","name":"Aposthol","steamID":"STEAM_0:0:444629814","team":"Santa Ana","matches":1,"wins":1,"losses":0,"draws":0,"goals":0,"assists":0,"shots":0,"shotsontarget":0,"passes":8,"passescompleted":5,"interceptions":3,"saves":0,"fouls":0,"yellowcards":0,"redcards":0,"owngoals":0,"offsides":0,"distancecovered":2389,"possession":5,"corners":0,"throwins":0,"penalties":0,"freekicks":0,"tackles":0,"tacklescompleted":0,"foulssuffered":0,"savescaught":0,"goalkicks":0,"goalsconceded":0,"secondsplayed":2037,"keypasses":0,"chancescreated":0,"secondassists":0},{"_id":"STEAM_0:1:4812742","name":"Fallen","steamID":"STEAM_0:1:4812742","team":"Santa Ana","matches":6,"wins":2,"losses":4,"draws":0,"goals":3,"assists":1,"shots":11,"shotsontarget":11,"passes":22,"passescompleted":10,"interceptions":4,"saves":0,"fouls":0,"yellowcards":0,"redcards":0,"owngoals":0,"offsides":2,"distancecovered":1608.6666666666667,"possession":2.8333333333333335,"corners":0,"throwins":2,"penalties":0,"freekicks":0,"tackles":0,"tacklescompleted":0,"foulssuffered":0,"savescaught":0,"goalkicks":0,"goalsconceded":0,"secondsplayed":31759,"keypasses":0,"chancescreated":0,"secondassists":0},{"_id":"STEAM_0:1:215641887","name":"Lox :)","steamID":"STEAM_0:1:215641887","team":"Santa Ana","matches":15,"wins":7,"losses":7,"draws":1,"goals":28,"assists":17,"shots":98,"shotsontarget":72,"passes":497,"passescompleted":325,"interceptions":142,"saves":0,"fouls":0,"yellowcards":0,"redcards":0,"owngoals":0,"offsides":3,"distancecovered":7486.8,"possession":13.133333333333333,"corners":21,"throwins":46,"penalties":1,"freekicks":14,"tackles":12,"tacklescompleted":2,"foulssuffered":6,"savescaught":0,"goalkicks":0,"goalsconceded":0,"secondsplayed":85435,"keypasses":0,"chancescreated":0,"secondassists":0},{"_id":"STEAM_0:0:69043478","name":"MattiasLp","steamID":"STEAM_0:0:69043478","team":"Santa Ana","matches":18,"wins":9,"losses":8,"draws":1,"goals":0,"assists":5,"shots":7,"shotsontarget":2,"passes":361,"passescompleted":196,"interceptions":132,"saves":103,"fouls":0,"yellowcards":0,"redcards":0,"owngoals":0,"offsides":0,"distancecovered":2420.277777777778,"possession":4.5,"corners":0,"throwins":0,"penalties":0,"freekicks":1,"tackles":0,"tacklescompleted":0,"foulssuffered":0,"savescaught":64,"goalkicks":127,"goalsconceded":53,"secondsplayed":147058,"keypasses":0,"chancescreated":0,"secondassists":0},{"_id":"STEAM_0:1:55575795","name":"pitusa","steamID":"STEAM_0:1:55575795","team":"Santa Ana","matches":16,"wins":8,"losses":7,"draws":1,"goals":17,"assists":6,"shots":57,"shotsontarget":48,"passes":617,"passescompleted":368,"interceptions":258,"saves":3,"fouls":0,"yellowcards":0,"redcards":0,"owngoals":0,"offsides":0,"distancecovered":6679.9375,"possession":12.6875,"corners":2,"throwins":52,"penalties":1,"freekicks":8,"tackles":19,"tacklescompleted":8,"foulssuffered":3,"savescaught":3,"goalkicks":2,"goalsconceded":1,"secondsplayed":81100,"keypasses":0,"chancescreated":0,"secondassists":0},{"_id":"STEAM_0:0:97705158","name":"richardS9","steamID":"STEAM_0:0:97705158","team":"Santa Ana","matches":12,"wins":6,"losses":5,"draws":1,"goals":16,"assists":15,"shots":44,"shotsontarget":36,"passes":295,"passescompleted":201,"interceptions":85,"saves":0,"fouls":0,"yellowcards":0,"redcards":0,"owngoals":0,"offsides":8,"distancecovered":6513.333333333333,"possession":11.166666666666666,"corners":14,"throwins":52,"penalties":0,"freekicks":4,"tackles":2,"tacklescompleted":1,"foulssuffered":1,"savescaught":0,"goalkicks":1,"goalsconceded":0,"secondsplayed":138274,"keypasses":0,"chancescreated":0,"secondassists":0},{"_id":"STEAM_0:1:445699118","name":"rorro","steamID":"STEAM_0:1:445699118","team":"Santa Ana","matches":12,"wins":6,"losses":5,"draws":1,"goals":11,"assists":12,"shots":46,"shotsontarget":27,"passes":326,"passescompleted":217,"interceptions":89,"saves":0,"fouls":1,"yellowcards":0,"redcards":0,"owngoals":0,"offsides":2,"distancecovered":5693.083333333333,"possession":14.75,"corners":18,"throwins":33,"penalties":2,"freekicks":2,"tackles":16,"tacklescompleted":6,"foulssuffered":1,"savescaught":0,"goalkicks":1,"goalsconceded":0,"secondsplayed":52047,"keypasses":0,"chancescreated":0,"secondassists":0},{"_id":"STEAM_0:1:92099918","name":"xEIRT'.","steamID":"STEAM_0:1:92099918","team":"Santa Ana","matches":5,"wins":3,"losses":2,"draws":0,"goals":0,"assists":1,"shots":0,"shotsontarget":0,"passes":102,"passescompleted":40,"interceptions":41,"saves":0,"fouls":1,"yellowcards":1,"redcards":0,"owngoals":0,"offsides":0,"distancecovered":4846.2,"possession":5.8,"corners":0,"throwins":13,"penalties":0,"freekicks":2,"tackles":13,"tacklescompleted":5,"foulssuffered":0,"savescaught":0,"goalkicks":0,"goalsconceded":0,"secondsplayed":18780,"keypasses":0,"chancescreated":0,"secondassists":0},{"_id":"STEAM_0:1:42002976","name":"Facu","steamID":"STEAM_0:1:42002976","team":"Union Deportivo Empate","matches":16,"wins":7,"losses":8,"draws":1,"goals":4,"assists":23,"shots":57,"shotsontarget":40,"passes":518,"passescompleted":250,"interceptions":289,"saves":0,"fouls":2,"yellowcards":2,"redcards":0,"owngoals":0,"offsides":0,"distancecovered":6891.4375,"possession":11.75,"corners":8,"throwins":77,"penalties":0,"freekicks":11,"tackles":68,"tacklescompleted":25,"foulssuffered":3,"savescaught":0,"goalkicks":0,"goalsconceded":0,"secondsplayed":173999,"keypasses":0,"chancescreated":0,"secondassists":0},{"_id":"STEAM_0:1:30338117","name":"Gonzalo","steamID":"STEAM_0:1:30338117","team":"Union Deportivo Empate","matches":15,"wins":9,"losses":5,"draws":1,"goals":48,"assists":8,"shots":176,"shotsontarget":133,"passes":369,"passescompleted":156,"interceptions":93,"saves":0,"fouls":5,"yellowcards":5,"redcards":2,"owngoals":0,"offsides":17,"distancecovered":7034.8,"possession":9.733333333333333,"corners":18,"throwins":23,"penalties":1,"freekicks":4,"tackles":73,"tacklescompleted":9,"foulssuffered":2,"savescaught":0,"goalkicks":1,"goalsconceded":0,"secondsplayed":149439,"keypasses":0,"chancescreated":0,"secondassists":0},{"_id":"STEAM_0:0:41134189","name":"Jazz","steamID":"STEAM_0:0:41134189","team":"Union Deportivo Empate","matches":14,"wins":9,"losses":4,"draws":1,"goals":4,"assists":7,"shots":33,"shotsontarget":16,"passes":496,"passescompleted":210,"interceptions":225,"saves":8,"fouls":3,"yellowcards":3,"redcards":0,"owngoals":0,"offsides":0,"distancecovered":7366.142857142857,"possession":8.928571428571429,"corners":7,"throwins":64,"penalties":0,"freekicks":3,"tackles":24,"tacklescompleted":6,"foulssuffered":0,"savescaught":6,"goalkicks":10,"goalsconceded":3,"secondsplayed":150954,"keypasses":0,"chancescreated":0,"secondassists":0},{"_id":"STEAM_0:1:82610399","name":"Josely","steamID":"STEAM_0:1:82610399","team":"Union Deportivo Empate","matches":14,"wins":7,"losses":6,"draws":1,"goals":28,"assists":16,"shots":92,"shotsontarget":69,"passes":331,"passescompleted":195,"interceptions":138,"saves":0,"fouls":0,"yellowcards":0,"redcards":0,"owngoals":0,"offsides":2,"distancecovered":6135.071428571428,"possession":13.428571428571429,"corners":14,"throwins":37,"penalties":0,"freekicks":7,"tackles":46,"tacklescompleted":10,"foulssuffered":2,"savescaught":0,"goalkicks":1,"goalsconceded":0,"secondsplayed":139684,"keypasses":0,"chancescreated":0,"secondassists":0},{"_id":"STEAM_0:1:46315289","name":"Lixtinhos","steamID":"STEAM_0:1:46315289","team":"Union Deportivo Empate","matches":4,"wins":1,"losses":3,"draws":0,"goals":10,"assists":3,"shots":29,"shotsontarget":20,"passes":132,"passescompleted":93,"interceptions":31,"saves":0,"fouls":3,"yellowcards":2,"redcards":1,"owngoals":0,"offsides":0,"distancecovered":5635,"possession":13,"corners":3,"throwins":10,"penalties":0,"freekicks":4,"tackles":19,"tacklescompleted":0,"foulssuffered":1,"savescaught":0,"goalkicks":0,"goalsconceded":0,"secondsplayed":16950,"keypasses":0,"chancescreated":0,"secondassists":0},{"_id":"STEAM_0:1:54601973","name":"LuXeM","steamID":"STEAM_0:1:54601973","team":"Union Deportivo Empate","matches":14,"wins":6,"losses":7,"draws":1,"goals":31,"assists":14,"shots":77,"shotsontarget":64,"passes":269,"passescompleted":135,"interceptions":102,"saves":14,"fouls":1,"yellowcards":1,"redcards":0,"owngoals":0,"offsides":4,"distancecovered":6350.714285714285,"possession":9.285714285714286,"corners":11,"throwins":32,"penalties":0,"freekicks":4,"tackles":27,"tacklescompleted":4,"foulssuffered":1,"savescaught":10,"goalkicks":21,"goalsconceded":4,"secondsplayed":159212,"keypasses":0,"chancescreated":0,"secondassists":0},{"_id":"STEAM_0:1:170699362","name":"Patanga","steamID":"STEAM_0:1:170699362","team":"Union Deportivo Empate","matches":13,"wins":5,"losses":8,"draws":0,"goals":0,"assists":7,"shots":9,"shotsontarget":4,"passes":313,"passescompleted":205,"interceptions":147,"saves":82,"fouls":0,"yellowcards":0,"redcards":0,"owngoals":0,"offsides":0,"distancecovered":4877.384615384615,"possession":5.6923076923076925,"corners":0,"throwins":0,"penalties":0,"freekicks":0,"tackles":1,"tacklescompleted":0,"foulssuffered":0,"savescaught":59,"goalkicks":77,"goalsconceded":24,"secondsplayed":156329,"keypasses":0,"chancescreated":0,"secondassists":0},{"_id":"STEAM_0:0:223905526","name":"Bathistuta","steamID":"STEAM_0:0:223905526","team":"X-Squadron FC","matches":3,"wins":1,"losses":2,"draws":0,"goals":2,"assists":0,"shots":14,"shotsontarget":9,"passes":29,"passescompleted":10,"interceptions":7,"saves":0,"fouls":0,"yellowcards":0,"redcards":0,"owngoals":0,"offsides":5,"distancecovered":4764.333333333333,"possession":5.666666666666667,"corners":1,"throwins":2,"penalties":0,"freekicks":1,"tackles":14,"tacklescompleted":1,"foulssuffered":1,"savescaught":0,"goalkicks":0,"goalsconceded":0,"secondsplayed":132338,"keypasses":0,"chancescreated":0,"secondassists":0},{"_id":"STEAM_0:0:15616105","name":"Normanspan","steamID":"STEAM_0:0:15616105","team":"X-Squadron FC","matches":1,"wins":1,"losses":0,"draws":0,"goals":1,"assists":1,"shots":6,"shotsontarget":5,"passes":26,"passescompleted":16,"interceptions":6,"saves":0,"fouls":0,"yellowcards":0,"redcards":0,"owngoals":0,"offsides":2,"distancecovered":7632,"possession":7,"corners":1,"throwins":3,"penalties":0,"freekicks":2,"tackles":26,"tacklescompleted":1,"foulssuffered":0,"savescaught":0,"goalkicks":0,"goalsconceded":0,"secondsplayed":56352,"keypasses":0,"chancescreated":0,"secondassists":0},{"_id":"STEAM_0:0:420453381","name":"PastorDeSapos","steamID":"STEAM_0:0:420453381","team":"X-Squadron FC","matches":2,"wins":0,"losses":2,"draws":0,"goals":0,"assists":0,"shots":1,"shotsontarget":1,"passes":20,"passescompleted":9,"interceptions":7,"saves":0,"fouls":1,"yellowcards":1,"redcards":0,"owngoals":0,"offsides":0,"distancecovered":4357.5,"possession":4.5,"corners":0,"throwins":3,"penalties":0,"freekicks":4,"tackles":18,"tacklescompleted":1,"foulssuffered":0,"savescaught":0,"goalkicks":0,"goalsconceded":0,"secondsplayed":74327,"keypasses":0,"chancescreated":0,"secondassists":0},{"_id":"STEAM_0:1:219757104","name":"Theustopable","steamID":"STEAM_0:1:219757104","team":"X-Squadron FC","matches":3,"wins":1,"losses":2,"draws":0,"goals":0,"assists":0,"shots":3,"shotsontarget":2,"passes":77,"passescompleted":26,"interceptions":21,"saves":0,"fouls":3,"yellowcards":2,"redcards":1,"owngoals":0,"offsides":0,"distancecovered":5018.666666666667,"possession":13,"corners":0,"throwins":10,"penalties":0,"freekicks":1,"tackles":26,"tacklescompleted":3,"foulssuffered":0,"savescaught":0,"goalkicks":0,"goalsconceded":0,"secondsplayed":10942,"keypasses":0,"chancescreated":0,"secondassists":0}]